dynalite_devices_lib/__init__.py
dynalite_devices_lib/__version__.py
dynalite_devices_lib/config.py
dynalite_devices_lib/const.py
dynalite_devices_lib/cover.py
dynalite_devices_lib/dynalite.py
dynalite_devices_lib/dynalite_devices.py
dynalite_devices_lib/dynalitebase.py
dynalite_devices_lib/dynet.py
dynalite_devices_lib/event.py
dynalite_devices_lib/inbound.py
dynalite_devices_lib/light.py
dynalite_devices_lib/opcodes.py
dynalite_devices_lib/switch.py
dynalite_devices-0.1.48.dist-info/LICENSE.md
dynalite_devices-0.1.48.dist-info/METADATA
dynalite_devices-0.1.48.dist-info/WHEEL
dynalite_devices-0.1.48.dist-info/top_level.txt
dynalite_devices-0.1.48.dist-info/RECORD
